LICENSE
MANIFEST.in
README.md
README.rst
config.py
run.py
setup.cfg
setup.py
sqmpy.db
sqmpy/__init__.py
sqmpy/default_config.py
sqmpy/views.py
sqmpy.egg-info/PKG-INFO
sqmpy.egg-info/SOURCES.txt
sqmpy.egg-info/dependency_links.txt
sqmpy.egg-info/not-zip-safe
sqmpy.egg-info/requires.txt
sqmpy.egg-info/top_level.txt
sqmpy/core/__init__.py
sqmpy/job/__init__.py
sqmpy/job/constants.py
sqmpy/job/exceptions.py
sqmpy/job/forms.py
sqmpy/job/helpers.py
sqmpy/job/manager.py
sqmpy/job/models.py
sqmpy/job/saga_helper.py
sqmpy/job/services.py
sqmpy/job/views.py
sqmpy/security/__init__.py
sqmpy/security/constants.py
sqmpy/security/exceptions.py
sqmpy/security/forms.py
sqmpy/security/manager.py
sqmpy/security/models.py
sqmpy/security/services.py
sqmpy/security/views.py
sqmpy/static/style.css
sqmpy/static/css/bootstrap-theme.css
sqmpy/static/css/bootstrap-theme.css.map
sqmpy/static/css/bootstrap-theme.min.css
sqmpy/static/css/bootstrap.css
sqmpy/static/css/bootstrap.css.map
sqmpy/static/css/bootstrap.min.css
sqmpy/static/css/signin.css
sqmpy/static/css/style.css
sqmpy/static/fonts/glyphicons-halflings-regular.eot
sqmpy/static/fonts/glyphicons-halflings-regular.svg
sqmpy/static/fonts/glyphicons-halflings-regular.ttf
sqmpy/static/fonts/glyphicons-halflings-regular.woff
sqmpy/static/js/bootstrap.js
sqmpy/static/js/bootstrap.min.js
sqmpy/templates/_formhelpers.html
sqmpy/templates/_paginationhelper.html
sqmpy/templates/index.html
sqmpy/templates/layout.html
sqmpy/templates/job/job_base.html
sqmpy/templates/job/job_detail.html
sqmpy/templates/job/job_list.html
sqmpy/templates/job/job_submit.html
sqmpy/templates/security/login.html
sqmpy/templates/security/register.html