Metadata-Version: 1.1
Name: sqmpy
Version: v1.0.0-alpha.3
Summary: Simple Queue Manager, also sqmpy, is a web interface for submitting jobs to HPC resources.
Home-page: http://github.com/mehdix/simple-queue-manager
Author: Mehdi Sadeghi
Author-email: sade@iwm.fraunhofer.de
License: BSD
Platform: UNKNOWN
Classifier: Development Status :: 2 - Pre-Alpha
Classifier: Intended Audience :: Science/Research
Classifier: Natural Language :: English
Classifier: License :: OSI Approved :: BSD License
Classifier: Operating System :: POSIX :: Linux
Classifier: Programming Language :: Python
Classifier: Programming Language :: Python :: 2.7
Classifier: Topic :: Internet :: WWW/HTTP :: WSGI :: Application
